django_allauth_vatsim/__init__.py
django_allauth_vatsim/adapter.py
django_allauth_vatsim/apps.py
django_allauth_vatsim/provider.py
django_allauth_vatsim/urls.py
django_allauth_vatsim/views.py
django_allauth_vatsim-0.0.3.dist-info/LICENSE
django_allauth_vatsim-0.0.3.dist-info/METADATA
django_allauth_vatsim-0.0.3.dist-info/WHEEL
django_allauth_vatsim-0.0.3.dist-info/top_level.txt
django_allauth_vatsim-0.0.3.dist-info/RECORD
