Metadata-Version: 2.1
Name: django-allauth-vatsim
Version: 0.0.3
Summary: OAuth2 login provider for VATSIM using django-allauth.
Author-email: Robin Kipp <robin@robin-kipp.net>
Project-URL: Homepage, https://github.com/robin24/django-allauth-vatsim
Project-URL: Issues, https://github.com/robin24/django-allauth-vatsim/issues
Keywords: vatsim,vatsim-oauth
Classifier: Development Status :: 4 - Beta
Classifier: Programming Language :: Python :: 3
Classifier: Topic :: Software Development :: Libraries :: Python Modules
Classifier: Environment :: Web Environment
Classifier: Topic :: Internet
Classifier: License :: OSI Approved :: BSD License
Classifier: Intended Audience :: Developers
Classifier: Operating System :: OS Independent
Classifier: Framework :: Django
Classifier: Framework :: Django :: 4.0
Classifier: Framework :: Django :: 4.1
Classifier: Framework :: Django :: 5.0
Requires-Python: >=3.10
License-File: LICENSE
Requires-Dist: django-allauth >=0.62.0
